{
  "workspace": {
    "name": "packages",
    "scope": "recalibratedsystems",
    "registry": "npm",
    "packages": [
      {
        "name": "nestjs-crud-util"
      },
      {
        "name": "nestjs-crud-request"
      },
      {
        "name": "nestjs-crud-typeorm"
      },
      {
        "name": "nestjs-crud"
      }
    ]
  },
  "packageGenerator": {
    "subGenerators": [],
    "defaultOptions": {
      "access": "public",
      "license": "MIT",
      "authorName": "Michael Yali",
      "authorEmail": "mihon4ik@gmail.com",
      "updateTsconfig": true,
      "subGenerators": [],
      "dependencies": []
    }
  }
}
